woolf/__init__.py
woolf/featureCSVfromFASTA.py
woolf/featureTable.py
woolf/trainWoolf.py
woolf/woolfClassifier.py
woolf-0.1.1.data/scripts/featureTable
woolf-0.1.1.data/scripts/trainWoolf
woolf-0.1.1.data/scripts/woolf_featureCSVfromFASTA.py
woolf-0.1.1.data/scripts/woolf_trainWoolf.py
woolf-0.1.1.dist-info/LICENSE
woolf-0.1.1.dist-info/METADATA
woolf-0.1.1.dist-info/WHEEL
woolf-0.1.1.dist-info/top_level.txt
woolf-0.1.1.dist-info/RECORD
